insurance_predictor/__init__.py
insurance_predictor/predictor.py
insurance_predictor/data/model.json
insurance_predictor-0.1.dist-info/METADATA
insurance_predictor-0.1.dist-info/WHEEL
insurance_predictor-0.1.dist-info/top_level.txt
insurance_predictor-0.1.dist-info/RECORD
